ipydistbuilder/__init__.py
ipydistbuilder/_version.py
ipydistbuilder/example.py
ipydistbuilder/static/extension.js
ipydistbuilder/static/index.js
ipydistbuilder/static/index.js.map
ipydistbuilder-0.1.11.dev0.data/data/share/jupyter/nbextensions/ipydistbuilder/extension.js
ipydistbuilder-0.1.11.dev0.data/data/share/jupyter/nbextensions/ipydistbuilder/index.js
ipydistbuilder-0.1.11.dev0.data/data/share/jupyter/nbextensions/ipydistbuilder/index.js.map
ipydistbuilder-0.1.11.dev0.dist-info/DESCRIPTION.rst
ipydistbuilder-0.1.11.dev0.dist-info/METADATA
ipydistbuilder-0.1.11.dev0.dist-info/RECORD
ipydistbuilder-0.1.11.dev0.dist-info/WHEEL
ipydistbuilder-0.1.11.dev0.dist-info/metadata.json
ipydistbuilder-0.1.11.dev0.dist-info/top_level.txt
