Metadata-Version: 2.0
Name: ipydistbuilder
Version: 0.1.11.dev0
Summary: A Jupyter widget to visualize distribution builders
Home-page: http://jupyter.org
Author: Quentin Andre
Author-email: quentin.andre@insead.edu
License: UNKNOWN
Keywords: ipython,jupyter,widgets
Platform: UNKNOWN
Classifier: Development Status :: 4 - Beta
Classifier: Framework :: IPython
Classifier: Intended Audience :: Developers
Classifier: Intended Audience :: Science/Research
Classifier: Topic :: Multimedia :: Graphics
Classifier: Programming Language :: Python :: 2
Classifier: Programming Language :: Python :: 2.7
Classifier: Programming Language :: Python :: 3
Classifier: Programming Language :: Python :: 3.3
Classifier: Programming Language :: Python :: 3.4
Classifier: Programming Language :: Python :: 3.5
Requires-Dist: ipywidgets (>=6.0.0)
